cltoolkit/__init__.py
cltoolkit/log.py
cltoolkit/models.py
cltoolkit/util.py
cltoolkit/wordlist.py
cltoolkit/features/__init__.py
cltoolkit/features/collection.py
cltoolkit/features/lexicon.py
cltoolkit/features/phonology.py
cltoolkit/features/reqs.py
cltoolkit/features/util.py
cltoolkit-0.2.0.dist-info/LICENSE
cltoolkit-0.2.0.dist-info/METADATA
cltoolkit-0.2.0.dist-info/WHEEL
cltoolkit-0.2.0.dist-info/top_level.txt
cltoolkit-0.2.0.dist-info/RECORD
