Metadata-Version: 2.1
Name: cltoolkit
Version: 0.2.0
Summary: A Python Library for the Processing of Cross-Linguistic Data
Home-page: https://github.com/cldf/cltoolkit
Author: Johann-Mattis List, Robert Forkel and Frederic Blum
Author-email: robert_forkel@eva.mpg.de
License: MIT
Project-URL: Bug Tracker, https://github.com/cldf/cltoolkit/issues
Keywords: linguistics
Platform: any
Classifier: Development Status :: 5 - Production/Stable
Classifier: Intended Audience :: Developers
Classifier: Intended Audience :: Science/Research
Classifier: Natural Language :: English
Classifier: Operating System :: OS Independent
Classifier: Programming Language :: Python :: 3
Classifier: Programming Language :: Python :: 3.8
Classifier: Programming Language :: Python :: 3.9
Classifier: Programming Language :: Python :: 3.10
Classifier: Programming Language :: Python :: 3.11
Classifier: Programming Language :: Python :: 3.12
Classifier: Programming Language :: Python :: 3.13
Classifier: Programming Language :: Python :: Implementation :: CPython
Classifier: Programming Language :: Python :: Implementation :: PyPy
Requires-Python: >=3.8
License-File: LICENSE
Requires-Dist: attrs>=18.2
Requires-Dist: clldutils>=3.5
Requires-Dist: csvw>=1.6
Requires-Dist: pycldf
Requires-Dist: uritemplate
Requires-Dist: lingpy>=2.6.5
Requires-Dist: pyclts>=3.1
Provides-Extra: dev
Requires-Dist: tox; extra == "dev"
Requires-Dist: flake8; extra == "dev"
Requires-Dist: wheel>=0.36; extra == "dev"
Requires-Dist: twine; extra == "dev"
Provides-Extra: test
Requires-Dist: pytest>=6; extra == "test"
Requires-Dist: pytest-mock; extra == "test"
Requires-Dist: pytest-cov; extra == "test"
Requires-Dist: coverage; extra == "test"
Requires-Dist: pyconcepticon; extra == "test"
